stk_mcp/__init__.py
stk_mcp/server.py
stk_mcp/stk_logic/core.py
stk_mcp/stk_logic/satellite.py
stk_mcp/stk_logic/scenario.py
stk_mcp/tools/__init__.py
stk_mcp/tools/satellite.py
stk_mcp/tools/scenario.py
mseep_stk_mcp-0.1.4.dist-info/METADATA
mseep_stk_mcp-0.1.4.dist-info/WHEEL
mseep_stk_mcp-0.1.4.dist-info/top_level.txt
mseep_stk_mcp-0.1.4.dist-info/RECORD
