Metadata-Version: 2.4
Name: mseep-stk-mcp
Version: 0.1.4
Summary: STK-MCP, an MCP server allowing LLMs to interact with Ansys/AGI STK - Digital Mission Engineering Software
Author-email: mseep <support@skydeck.ai>
Requires-Python: >=3.12
Requires-Dist: mcp[cli]>=1.6.0
